[{
    "num_tema": 1,
    "tema": "Hablando matemáticamente",
    "libro_teorico": "https://drive.google.com/file/d/1tcnAZz4nyPIrzNkRZyF5Bvv8PT26l3do/view?usp=sharing",
    "libro_practico": "https://drive.google.com/file/d/1okkT-ndg1vOiPzTGXyWTVjgBXcCt1Q1p/view?usp=sharing",
    "name_video": "TIPOS DE NÚMEROS CLASIFICACIÓN  Matemáticas Básicas",
    "link_video": "https://youtu.be/8K8sHLEhj14?si=Hs4AcbSfbOM-X7iz",
    "name_video2": "Símbolos usados en conjuntos",
    "link_video2": "https://www.youtube.com/watch?v=MY24oAocK4c",
    "link_form": "none"
  },
  {
    "num_tema": 2,
    "tema": "Hablando matemáticamente",
    "libro_teorico": "https://drive.google.com/file/d/1tcnAZz4nyPIrzNkRZyF5Bvv8PT26l3do/view?usp=sharing",
    "libro_practico": "https://drive.google.com/file/d/1okkT-ndg1vOiPzTGXyWTVjgBXcCt1Q1p/view?usp=sharing",
    "name_video": "TIPOS DE NÚMEROS CLASIFICACIÓN  Matemáticas Básicas",
    "link_video": "https://youtu.be/8K8sHLEhj14?si=Hs4AcbSfbOM-X7iz",
    "name_video2": "Símbolos usados en conjuntos",
    "link_video2": "https://www.youtube.com/watch?v=MY24oAocK4c",
    "link_form": "none"
  },
  {
    "num_tema": 3,
    "tema": "Hablando matemáticamente",
    "libro_teorico": "https://drive.google.com/file/d/1tcnAZz4nyPIrzNkRZyF5Bvv8PT26l3do/view?usp=sharing",
    "libro_practico": "https://drive.google.com/file/d/1okkT-ndg1vOiPzTGXyWTVjgBXcCt1Q1p/view?usp=sharing",
    "name_video": "TIPOS DE NÚMEROS CLASIFICACIÓN  Matemáticas Básicas",
    "link_video": "https://youtu.be/8K8sHLEhj14?si=Hs4AcbSfbOM-X7iz",
    "name_video2": "Símbolos usados en conjuntos",
    "link_video2": "https://www.youtube.com/watch?v=MY24oAocK4c",
    "link_form": "none"
  },
  {
    "num_tema": 4,
    "tema": "Hablando matemáticamente",
    "libro_teorico": "https://drive.google.com/file/d/1tcnAZz4nyPIrzNkRZyF5Bvv8PT26l3do/view?usp=sharing",
    "libro_practico": "https://drive.google.com/file/d/1okkT-ndg1vOiPzTGXyWTVjgBXcCt1Q1p/view?usp=sharing",
    "name_video": "TIPOS DE NÚMEROS CLASIFICACIÓN  Matemáticas Básicas",
    "link_video": "https://youtu.be/8K8sHLEhj14?si=Hs4AcbSfbOM-X7iz",
    "name_video2": "Símbolos usados en conjuntos",
    "link_video2": "https://www.youtube.com/watch?v=MY24oAocK4c",
    "link_form": "none"
  },
  {
    "num_tema": 5,
    "tema": "Hablando matemáticamente",
    "libro_teorico": "https://drive.google.com/file/d/1tcnAZz4nyPIrzNkRZyF5Bvv8PT26l3do/view?usp=sharing",
    "libro_practico": "https://drive.google.com/file/d/1okkT-ndg1vOiPzTGXyWTVjgBXcCt1Q1p/view?usp=sharing",
    "name_video": "TIPOS DE NÚMEROS CLASIFICACIÓN  Matemáticas Básicas",
    "link_video": "https://youtu.be/8K8sHLEhj14?si=Hs4AcbSfbOM-X7iz",
    "name_video2": "Símbolos usados en conjuntos",
    "link_video2": "https://www.youtube.com/watch?v=MY24oAocK4c",
    "link_form": "none"
  },
  {
    "num_tema": 6,
    "tema": "Hablando matemáticamente",
    "libro_teorico": "https://drive.google.com/file/d/1tcnAZz4nyPIrzNkRZyF5Bvv8PT26l3do/view?usp=sharing",
    "libro_practico": "https://drive.google.com/file/d/1okkT-ndg1vOiPzTGXyWTVjgBXcCt1Q1p/view?usp=sharing",
    "name_video": "TIPOS DE NÚMEROS CLASIFICACIÓN  Matemáticas Básicas",
    "link_video": "https://youtu.be/8K8sHLEhj14?si=Hs4AcbSfbOM-X7iz",
    "name_video2": "Símbolos usados en conjuntos",
    "link_video2": "https://www.youtube.com/watch?v=MY24oAocK4c",
    "link_form": "none"
  },
  {
    "num_tema": 7,
    "tema": "Hablando matemáticamente",
    "libro_teorico": "https://drive.google.com/file/d/1tcnAZz4nyPIrzNkRZyF5Bvv8PT26l3do/view?usp=sharing",
    "libro_practico": "https://drive.google.com/file/d/1okkT-ndg1vOiPzTGXyWTVjgBXcCt1Q1p/view?usp=sharing",
    "name_video": "TIPOS DE NÚMEROS CLASIFICACIÓN  Matemáticas Básicas",
    "link_video": "https://youtu.be/8K8sHLEhj14?si=Hs4AcbSfbOM-X7iz",
    "name_video2": "Símbolos usados en conjuntos",
    "link_video2": "https://www.youtube.com/watch?v=MY24oAocK4c",
    "link_form": "none"
  },
  {
    "num_tema": 8,
    "tema": "Hablando matemáticamente",
    "libro_teorico": "https://drive.google.com/file/d/1tcnAZz4nyPIrzNkRZyF5Bvv8PT26l3do/view?usp=sharing",
    "libro_practico": "https://drive.google.com/file/d/1okkT-ndg1vOiPzTGXyWTVjgBXcCt1Q1p/view?usp=sharing",
    "name_video": "TIPOS DE NÚMEROS CLASIFICACIÓN  Matemáticas Básicas",
    "link_video": "https://youtu.be/8K8sHLEhj14?si=Hs4AcbSfbOM-X7iz",
    "name_video2": "Símbolos usados en conjuntos",
    "link_video2": "https://www.youtube.com/watch?v=MY24oAocK4c",
    "link_form": "none"
  },
  {
    "num_tema": 9,
    "tema": "Hablando matemáticamente",
    "libro_teorico": "https://drive.google.com/file/d/1tcnAZz4nyPIrzNkRZyF5Bvv8PT26l3do/view?usp=sharing",
    "libro_practico": "https://drive.google.com/file/d/1okkT-ndg1vOiPzTGXyWTVjgBXcCt1Q1p/view?usp=sharing",
    "name_video": "TIPOS DE NÚMEROS CLASIFICACIÓN  Matemáticas Básicas",
    "link_video": "https://youtu.be/8K8sHLEhj14?si=Hs4AcbSfbOM-X7iz",
    "name_video2": "Símbolos usados en conjuntos",
    "link_video2": "https://www.youtube.com/watch?v=MY24oAocK4c",
    "link_form": "none"
  }
]